lorica/__init__.py
lorica/_attestor.py
lorica/session.py
lorica/transport.py
lorica/ohttp/__init__.py
lorica/ohttp/response_stream.py
lorica/ohttp/session.py
lorica/ohttp/transport.py
lorica-0.2a2.dist-info/METADATA
lorica-0.2a2.dist-info/WHEEL
lorica-0.2a2.dist-info/RECORD
