Metadata-Version: 2.4
Name: lorica
Version: 0.2a2
Summary: A python package to interact with products from Lorica Cybersecurity
Author-email: Lorica Cybersecurity <support@loricacyber.com>
Classifier: Operating System :: OS Independent
Classifier: Programming Language :: Python :: 3
Requires-Python: >=3.7
Requires-Dist: cachetools==5.5.2
Requires-Dist: ohttpy==0.1a13
Requires-Dist: pyjwt==2.10.1
